codetool.py
codetool/hash.py
codetool-0.21.dist-info/METADATA
codetool-0.21.dist-info/WHEEL
codetool-0.21.dist-info/top_level.txt
codetool-0.21.dist-info/RECORD
