Metadata-Version: 2.1
Name: codetool
Version: 0.21
Summary: Id generation, hash and encryption
Author: lolo859
Keywords: code,tool,codetool,hash,id,cdtl
Classifier: Natural Language :: French
Classifier: Topic :: Security :: Cryptography
Classifier: Topic :: Software Development :: Code Generators
